dynamic_i18n/__init__.py
dynamic_i18n/flatten.py
dynamic_i18n-0.0.7.dist-info/METADATA
dynamic_i18n-0.0.7.dist-info/WHEEL
dynamic_i18n-0.0.7.dist-info/top_level.txt
dynamic_i18n-0.0.7.dist-info/RECORD
