Metadata-Version: 2.1
Name: dynamic-i18n
Version: 0.0.7
Summary: A basic dynamic class to support I18N translation from JSON
Home-page: https://github.com/Jeferson-Peter/dynamic-i18n
Author: Jeferson-Peter (Jeferson Peter)
Author-email: jeferson.peter@pm.me
Keywords: Python,I18N,Translation,Dynamic Class,Flatten Json
Classifier: Development Status :: 1 - Planning
Classifier: Intended Audience :: Developers
Classifier: Programming Language :: Python :: 3.10
Classifier: Programming Language :: Python :: 3.11
Classifier: Operating System :: Unix
Classifier: Operating System :: MacOS :: MacOS X
Classifier: Operating System :: Microsoft :: Windows
